[
    {
        "key": "dbln",
        "value": "%7B%2261552814848384%22%3A%22bTO6VdvE%22%7D",
        "domain": "facebook.com",
        "path": "/login/device-based/",
        "hostOnly": false,
        "creation": "2025-04-11T17:06:35.972Z",
        "lastAccessed": "2025-04-11T17:06:35.978Z"
    },
    {
        "key": "sb",
        "value": "XBgcZ4fYdD7HXM9R-uSBTyFW",
        "domain": "facebook.com",
        "path": "/",
        "hostOnly": false,
        "creation": "2025-04-11T17:06:35.978Z",
        "lastAccessed": "2025-04-11T17:06:35.978Z"
    },
    {
        "key": "dpr",
        "value": "2.1988937854766846",
        "domain": "facebook.com",
        "path": "/",
        "hostOnly": false,
        "creation": "2025-04-11T17:06:35.978Z",
        "lastAccessed": "2025-04-11T17:06:35.978Z"
    },
    {
        "key": "ps_l",
        "value": "1",
        "domain": "facebook.com",
        "path": "/",
        "hostOnly": false,
        "creation": "2025-04-11T17:06:35.981Z",
        "lastAccessed": "2025-04-11T17:06:35.981Z"
    },
    {
        "key": "ps_n",
        "value": "1",
        "domain": "facebook.com",
        "path": "/",
        "hostOnly": false,
        "creation": "2025-04-11T17:06:35.981Z",
        "lastAccessed": "2025-04-11T17:06:35.981Z"
    },
    {
        "key": "locale",
        "value": "as_IN",
        "domain": "facebook.com",
        "path": "/",
        "hostOnly": false,
        "creation": "2025-04-11T17:06:35.981Z",
        "lastAccessed": "2025-04-11T17:06:35.981Z"
    },
    {
        "key": "datr",
        "value": "yOb4Z3nPk1VpVGKhRX055yrB",
        "domain": "facebook.com",
        "path": "/",
        "hostOnly": false,
        "creation": "2025-04-11T17:06:35.981Z",
        "lastAccessed": "2025-04-11T17:06:35.981Z"
    },
    {
        "key": "wd",
        "value": "891x1654",
        "domain": "facebook.com",
        "path": "/",
        "hostOnly": false,
        "creation": "2025-04-11T17:06:35.981Z",
        "lastAccessed": "2025-04-11T17:06:35.981Z"
    },
    {
        "key": "c_user",
        "value": "61566311011541",
        "domain": "facebook.com",
        "path": "/",
        "hostOnly": false,
        "creation": "2025-04-11T17:06:35.981Z",
        "lastAccessed": "2025-04-11T17:06:35.981Z"
    },
    {
        "key": "xs",
        "value": "12%3AvJHpoL5r9Wvqvw%3A2%3A1744365291%3A-1%3A13443%3A%3AAcUGMu5xUvQII97CO9WGpKprzVDCT7LhF6CmA6uiyw",
        "domain": "facebook.com",
        "path": "/",
        "hostOnly": false,
        "creation": "2025-04-11T17:06:35.982Z",
        "lastAccessed": "2025-04-11T17:06:35.982Z"
    },
    {
        "key": "fr",
        "value": "1V6Ky7WD49GsS5oR9.AWcdp98lXOpxN5qRVmEhJMtKY6lzDfgjsgLQEr0evnHxq8Pc-6s.Bn-Uqx..AAA.0.0.Bn-Uq4.AWcFbUGjsarp1E_rAyCxnsnYwA0",
        "domain": "facebook.com",
        "path": "/",
        "hostOnly": false,
        "creation": "2025-04-11T17:06:35.982Z",
        "lastAccessed": "2025-04-11T17:06:35.982Z"
    },
    {
        "key": "presence",
        "value": "C%7B%22t3%22%3A%5B%5D%2C%22utc3%22%3A1744390853256%2C%22v%22%3A1%7D",
        "domain": "facebook.com",
        "path": "/",
        "hostOnly": false,
        "creation": "2025-04-11T17:06:35.982Z",
        "lastAccessed": "2025-04-11T17:06:35.982Z"
    }
]
